fluent_multiselect/__init__.py
fluent_multiselect/chips.py
fluent_multiselect/colors.py
fluent_multiselect/combobox.py
fluent_multiselect/config.py
fluent_multiselect/delegate.py
fluent_multiselect/py.typed
fluent_multiselect/styles.py
fluent_multiselect-0.1.0.dist-info/licenses/LICENSE
fluent_multiselect-0.1.0.dist-info/METADATA
fluent_multiselect-0.1.0.dist-info/WHEEL
fluent_multiselect-0.1.0.dist-info/top_level.txt
fluent_multiselect-0.1.0.dist-info/RECORD
