Metadata-Version: 2.4
Name: fluent_multiselect
Version: 0.1.0
Summary: A Windows 11 Fluent Design styled multi-select combo box for PyQt6
Author-email: mIcHyAmRaNe <6m63er17c@mozmail.com>
Maintainer-email: mIcHyAmRaNe <6m63er17c@mozmail.com>
License: MIT
Project-URL: Homepage, https://github.com/michyamrane/fluent_multiselect
Project-URL: Documentation, https://github.com/michyamrane/fluent_multiselect#readme
Project-URL: Repository, https://github.com/michyamrane/fluent_multiselect.git
Project-URL: Issues, https://github.com/michyamrane/fluent_multiselect/issues
Project-URL: Changelog, https://github.com/michyamrane/fluent_multiselect/blob/main/CHANGELOG.md
Keywords: pyqt6,combobox,multiselect,fluent,fluent-design,windows11,ui,widget,qt,gui
Classifier: Development Status :: 5 - Production/Stable
Classifier: Intended Audience :: Developers
Classifier: License :: OSI Approved :: MIT License
Classifier: Operating System :: OS Independent
Classifier: Programming Language :: Python :: 3
Classifier: Programming Language :: Python :: 3.9
Classifier: Programming Language :: Python :: 3.10
Classifier: Programming Language :: Python :: 3.11
Classifier: Programming Language :: Python :: 3.12
Classifier: Topic :: Software Development :: User Interfaces
Classifier: Topic :: Software Development :: Widget Sets
Classifier: Environment :: X11 Applications :: Qt
Classifier: Environment :: Win32 (MS Windows)
Classifier: Environment :: MacOS X
Requires-Python: >=3.9
License-File: LICENSE
Requires-Dist: PyQt6>=6.4.0
Provides-Extra: dev
Requires-Dist: pytest>=7.0; extra == "dev"
Requires-Dist: pytest-qt>=4.2; extra == "dev"
Requires-Dist: pytest-cov>=4.0; extra == "dev"
Requires-Dist: black>=23.0; extra == "dev"
Requires-Dist: isort>=5.12; extra == "dev"
Requires-Dist: mypy>=1.0; extra == "dev"
Requires-Dist: ruff>=0.1; extra == "dev"
Provides-Extra: docs
Requires-Dist: sphinx>=6.0; extra == "docs"
Requires-Dist: sphinx-rtd-theme>=1.2; extra == "docs"
Dynamic: license-file
